dedsec_decoder/__init__.py
dedsec_decoder/cli.py
dedsec_decoder/core/__init__.py
dedsec_decoder/core/binary.py
dedsec_decoder/core/display.py
dedsec_decoder/utils/__init__.py
dedsec_decoder/utils/terminal.py
dedsec_decode-1.0.0.dist-info/LICENSE
dedsec_decode-1.0.0.dist-info/METADATA
dedsec_decode-1.0.0.dist-info/WHEEL
dedsec_decode-1.0.0.dist-info/entry_points.txt
dedsec_decode-1.0.0.dist-info/top_level.txt
dedsec_decode-1.0.0.dist-info/RECORD
