Metadata-Version: 2.2
Name: dedsec-decode
Version: 1.0.0
Summary: DedSec Binary Encoding/Decoding Tool
Home-page: https://github.com/dedsecDS/dedsec-decoder
Author: DedSec
Author-email: DEDSECVIP@proton.me
Project-URL: Bug Reports, https://github.com/dedsecDS/dedsec-decoder/issues
Project-URL: Source, https://github.com/dedsecDS/dedsec-decoder
Keywords: dedsec,binary,encoder,decoder,security,Famous-Tech
Classifier: Development Status :: 3 - Alpha
Classifier: Intended Audience :: Developers
Classifier: Topic :: Security :: Cryptography
Classifier: License :: OSI Approved :: MIT License
Classifier: Programming Language :: Python :: 3
Classifier: Programming Language :: Python :: 3.6
Classifier: Programming Language :: Python :: 3.7
Classifier: Programming Language :: Python :: 3.8
Classifier: Programming Language :: Python :: 3.9
Classifier: Programming Language :: Python :: 3.10
Classifier: Programming Language :: Python :: 3.11
Classifier: Programming Language :: Python :: 3.12
Classifier: Operating System :: OS Independent
Requires-Python: >=3.6
License-File: LICENSE
Requires-Dist: pyfiglet>=0.8.post1
Requires-Dist: colorama>=0.4.6
Requires-Dist: user-agents>=2.2.0
Dynamic: author
Dynamic: author-email
Dynamic: classifier
Dynamic: description
Dynamic: description-content-type
Dynamic: home-page
Dynamic: keywords
Dynamic: project-url
Dynamic: requires-dist
Dynamic: requires-python
Dynamic: summary
